mapstp/__init__.py
mapstp/cli/__init__.py
mapstp/cli/mapstp_logging.py
mapstp/cli/runner.py
mapstp/data/default-material-index.xlsx
mapstp/data/extract-info-0.3.4.py
mapstp/data/materials.txt.zip
mapstp/exceptions.py
mapstp/extract_info.py
mapstp/materials.py
mapstp/materials_index.py
mapstp/merge.py
mapstp/py.typed
mapstp/save_table.py
mapstp/stp_parser.py
mapstp/tree.py
mapstp/utils/__init__.py
mapstp/utils/_io.py
mapstp/utils/_re.py
mapstp/utils/decode_russian_in_stp.py
mapstp/workflow.py
mapstp/workflow_sql.py
mapstp-1.0.3.dist-info/WHEEL
mapstp-1.0.3.dist-info/entry_points.txt
mapstp-1.0.3.dist-info/METADATA
mapstp-1.0.3.dist-info/RECORD
