Metadata-Version: 2.3
Name: mapstp
Version: 1.0.3
Summary: Transfers meta information from STP to MCNP
Keywords: STP,MCNP,SuperMC,SpaceClaim,GEOUNED
Author: dvp2015
Author-email: dvp2015 <dmitri_portnov@yahoo.com>
License: MIT
Classifier: Development Status :: 4 - Beta
Classifier: Environment :: Console
Classifier: Intended Audience :: Developers
Classifier: Intended Audience :: Science/Research
Classifier: Operating System :: OS Independent
Classifier: Topic :: Scientific/Engineering :: Physics
Classifier: Programming Language :: Python :: 3
Requires-Dist: click>=8.1.7
Requires-Dist: loguru>=0.7.2
Requires-Dist: numpy>=2.3.1
Requires-Dist: openpyxl>=3.0.9
Requires-Dist: pandas>=2.0.0
Requires-Python: >=3.11, <4
Project-URL: homepage, https://github.com/MC-kit/map-stp
Project-URL: repository, https://github.com/MC-kit/map-stp
